fortigate_config_parser-0.0.6.dist-info/DESCRIPTION.rst
fortigate_config_parser-0.0.6.dist-info/LICENSE.txt
fortigate_config_parser-0.0.6.dist-info/METADATA
fortigate_config_parser-0.0.6.dist-info/RECORD
fortigate_config_parser-0.0.6.dist-info/WHEEL
fortigate_config_parser-0.0.6.dist-info/metadata.json
fortigate_config_parser-0.0.6.dist-info/top_level.txt
fortigate_parser/__init__.py
fortigate_parser/__init__.pyc
fortigate_parser/main.py
fortigate_parser/parser.py
fortigate_parser/parser.pyc
fortigate_parser/test.py
tests/__init__.py
tests/unit_tests/__init__.py
tests/unit_tests/conftest.py
tests/unit_tests/helpers.py
tests/unit_tests/fortigate_parser/__init__.py
tests/unit_tests/fortigate_parser/test_toplevel_parser.py
