Metadata-Version: 2.0
Name: fortigate-config-parser
Version: 0.0.6
Summary: A parser and unparser for fortigate config files.
Home-page: https://github.com/acidjunk/fortigate-config-parser
Author: Rene Dohmen
Author-email: acidjunk@gmail.com
License: GPLv3 License
Keywords: fortigate config parser
Platform: UNKNOWN
Classifier: Development Status :: 2 - Pre-Alpha
Classifier: License :: OSI Approved :: GNU General Public License v3 (GPLv3)
Classifier: Intended Audience :: Developers
Classifier: Natural Language :: English
Classifier: Programming Language :: Python
Classifier: Programming Language :: Python :: 2.7
Classifier: Programming Language :: Python :: 3
Classifier: Programming Language :: Python :: 3.3
Classifier: Programming Language :: Python :: 3.4
Classifier: Programming Language :: Python :: 3.5
